wtok/__init__.py
wtok/__main__.py
wtok/cli.py
wtok-0.6.1.dist-info/LICENSE
wtok-0.6.1.dist-info/METADATA
wtok-0.6.1.dist-info/WHEEL
wtok-0.6.1.dist-info/entry_points.txt
wtok-0.6.1.dist-info/top_level.txt
wtok-0.6.1.dist-info/RECORD
