Metadata-Version: 2.1
Name: wtok
Version: 0.6.1
Summary: Count and truncate whisper text based on tokens
Home-page: https://github.com/proger/wtok
Author: Vol Kyrylov thanks to Simon Willison
License: Apache License, Version 2.0
Project-URL: Issues, https://github.com/proger/wtok/issues
Project-URL: CI, https://github.com/proger/wtok/actions
Project-URL: Changelog, https://github.com/proger/wtok/releases
Requires-Python: >=3.8
License-File: LICENSE
Requires-Dist: click
Requires-Dist: tiktoken
Requires-Dist: openai-whisper
